odoo/addons/l10n_th_sequence_be/README.rst
odoo/addons/l10n_th_sequence_be/__init__.py
odoo/addons/l10n_th_sequence_be/__manifest__.py
odoo/addons/l10n_th_sequence_be/i18n/l10n_th_sequence_be.pot
odoo/addons/l10n_th_sequence_be/models/__init__.py
odoo/addons/l10n_th_sequence_be/models/ir_sequence.py
odoo/addons/l10n_th_sequence_be/readme/CONTRIBUTORS.rst
odoo/addons/l10n_th_sequence_be/readme/DESCRIPTION.rst
odoo/addons/l10n_th_sequence_be/readme/HISTORY.rst
odoo/addons/l10n_th_sequence_be/static/description/icon.png
odoo/addons/l10n_th_sequence_be/static/description/index.html
odoo/addons/l10n_th_sequence_be/tests/__init__.py
odoo/addons/l10n_th_sequence_be/tests/test_ir_sequence.py
odoo/addons/l10n_th_sequence_be/views/ir_sequence_view.xml
odoo14_addon_l10n_th_sequence_be-14.0.1.0.1.dist-info/METADATA
odoo14_addon_l10n_th_sequence_be-14.0.1.0.1.dist-info/WHEEL
odoo14_addon_l10n_th_sequence_be-14.0.1.0.1.dist-info/top_level.txt
odoo14_addon_l10n_th_sequence_be-14.0.1.0.1.dist-info/RECORD
