Metadata-Version: 2.1
Name: odoo14-addon-l10n-th-sequence-be
Version: 14.0.1.0.1
Summary: Thai Localization - Sequence with Buddhist Era Year
Home-page: https://github.com/OCA/l10n-thailand
Author: Sansiri Tanachutiwat, Odoo Community Association (OCA)
Author-email: support@odoo-community.org
License: AGPL-3
Platform: UNKNOWN
Classifier: Programming Language :: Python
Classifier: Framework :: Odoo
Classifier: Framework :: Odoo :: 14.0
Classifier: License :: OSI Approved :: GNU Affero General Public License v3
Requires-Python: >=3.6
Requires-Dist: odoo14-addon-l10n-th-sequence-preview
Requires-Dist: odoo14-addon-l10n-th-sequence-refactored
Requires-Dist: odoo (<14.1dev,>=14.0a)
